pocketflow_tracing/__init__.py
pocketflow_tracing/config.py
pocketflow_tracing/core.py
pocketflow_tracing/decorator.py
pocketflow_tracing/utils.py
pocketflow_tracing/examples/__init__.py
pocketflow_tracing/examples/async_example.py
pocketflow_tracing/examples/basic_example.py
pocketflow_tracing-1.0.0.dist-info/licenses/LICENSE
pocketflow_tracing-1.0.0.dist-info/METADATA
pocketflow_tracing-1.0.0.dist-info/WHEEL
pocketflow_tracing-1.0.0.dist-info/entry_points.txt
pocketflow_tracing-1.0.0.dist-info/top_level.txt
pocketflow_tracing-1.0.0.dist-info/RECORD
