Metadata-Version: 2.4
Name: pocketflow-tracing
Version: 1.0.0
Summary: Observability and tracing for PocketFlow workflows using Langfuse
Home-page: https://github.com/The-Pocket/PocketFlow
Author: Zachary Huang
Author-email: PocketFlow Team <support@pocketflow.dev>
License: MIT
Project-URL: Homepage, https://github.com/The-Pocket/PocketFlow
Project-URL: Documentation, https://github.com/The-Pocket/PocketFlow/tree/main/cookbook/pocketflow-tracing
Project-URL: Repository, https://github.com/The-Pocket/PocketFlow
Project-URL: Bug Tracker, https://github.com/The-Pocket/PocketFlow/issues
Keywords: pocketflow,tracing,observability,langfuse,monitoring,workflow,debugging,analytics
Classifier: Development Status :: 4 - Beta
Classifier: Intended Audience :: Developers
Classifier: License :: OSI Approved :: MIT License
Classifier: Operating System :: OS Independent
Classifier: Programming Language :: Python :: 3
Classifier: Programming Language :: Python :: 3.8
Classifier: Programming Language :: Python :: 3.9
Classifier: Programming Language :: Python :: 3.10
Classifier: Programming Language :: Python :: 3.11
Classifier: Programming Language :: Python :: 3.12
Classifier: Topic :: Software Development :: Libraries :: Python Modules
Classifier: Topic :: System :: Monitoring
Classifier: Topic :: Software Development :: Debuggers
Requires-Python: >=3.8
License-File: LICENSE
Requires-Dist: langfuse<3.0.0,>=2.0.0
Requires-Dist: python-dotenv>=1.0.0
Requires-Dist: pydantic>=2.0.0
Provides-Extra: dev
Requires-Dist: pytest>=7.0.0; extra == "dev"
Requires-Dist: pytest-asyncio>=0.21.0; extra == "dev"
Requires-Dist: black>=23.0.0; extra == "dev"
Requires-Dist: isort>=5.12.0; extra == "dev"
Requires-Dist: flake8>=6.0.0; extra == "dev"
Requires-Dist: mypy>=1.0.0; extra == "dev"
Provides-Extra: examples
Requires-Dist: pocketflow>=0.0.1; extra == "examples"
Dynamic: author
Dynamic: home-page
Dynamic: license-file
